[
    {
        "g1": "Machine n1:\nGPU0 None  utilization -1%    mem -1GB/-1GB    temp -1\u00b0    User N/A"
    },
    {
        "g3": "Machine g3:\nGPU0 NVIDIA GeForce RTX 4090  utilization 0%    mem 0GB/24GB    temp 33\u00b0    User N/A\nGPU1 NVIDIA GeForce RTX 4090  utilization 0%    mem 0GB/24GB    temp 32\u00b0    User N/A\nGPU2 NVIDIA GeForce RTX 4090  utilization 0%    mem 0GB/24GB    temp 35\u00b0    User N/A\nGPU3 NVIDIA GeForce RTX 4090  utilization 0%    mem 0GB/24GB    temp 33\u00b0    User N/A\nGPU4 NVIDIA GeForce RTX 4090  utilization 0%    mem 0GB/24GB    temp 32\u00b0    User N/A\nGPU5 NVIDIA GeForce RTX 4090  utilization 0%    mem 0GB/24GB    temp 33\u00b0    User N/A\nGPU6 NVIDIA GeForce RTX 4090  utilization 0%    mem 0GB/24GB    temp 33\u00b0    User N/A\nGPU7 NVIDIA GeForce RTX 4090  utilization 0%    mem 0GB/24GB    temp 32\u00b0    User N/A"
    },
    {
        "g4": "Machine g4:\nGPU0 NVIDIA GeForce RTX 4090  utilization 69%    mem 44GB/48GB    temp 55\u00b0    User hxy\nGPU1 NVIDIA GeForce RTX 4090  utilization 60%    mem 44GB/48GB    temp 52\u00b0    User hxy\nGPU2 NVIDIA GeForce RTX 4090  utilization 58%    mem 44GB/48GB    temp 54\u00b0    User hxy\nGPU3 NVIDIA GeForce RTX 4090  utilization 72%    mem 44GB/48GB    temp 47\u00b0    User hxy\nGPU4 NVIDIA GeForce RTX 4090  utilization 0%    mem 45GB/48GB    temp 33\u00b0    User ryj\nGPU5 NVIDIA GeForce RTX 4090  utilization 0%    mem 45GB/48GB    temp 31\u00b0    User ryj\nGPU6 NVIDIA GeForce RTX 4090  utilization 0%    mem 45GB/48GB    temp 34\u00b0    User ryj\nGPU7 NVIDIA GeForce RTX 4090  utilization 0%    mem 45GB/48GB    temp 35\u00b0    User ryj"
    },
    {
        "a100-1": "Machine a100-1:\nGPU0 NVIDIA A100-SXM4-40GB  utilization 100%    mem 37GB/40GB    temp 37\u00b0    User ly\nGPU1 NVIDIA A100-SXM4-40GB  utilization 62%    mem 33GB/40GB    temp 36\u00b0    User ly\nGPU2 NVIDIA A100-SXM4-40GB  utilization 100%    mem 39GB/40GB    temp 37\u00b0    User ly\nGPU3 NVIDIA A100-SXM4-40GB  utilization 0%    mem 1GB/40GB    temp 31\u00b0    User N/A\nGPU4 NVIDIA A100-SXM4-40GB  utilization 0%    mem 1GB/40GB    temp 30\u00b0    User N/A\nGPU5 NVIDIA A100-SXM4-40GB  utilization 99%    mem 14GB/40GB    temp 67\u00b0    User cyy\nGPU6 NVIDIA A100-SXM4-40GB  utilization 99%    mem 15GB/40GB    temp 65\u00b0    User cyy\nGPU7 NVIDIA A100-SXM4-40GB  utilization 99%    mem 16GB/40GB    temp 68\u00b0    User cyy"
    },
    {
        "a100-2": "Machine a100-2:\nGPU0 NVIDIA A100-SXM4-40GB  utilization 0%    mem 10GB/40GB    temp 32\u00b0    User N/A\nGPU1 NVIDIA A100-SXM4-40GB  utilization 0%    mem 29GB/40GB    temp 32\u00b0    User N/A\nGPU2 NVIDIA A100-SXM4-40GB  utilization 100%    mem 38GB/40GB    temp 34\u00b0    User N/A\nGPU3 NVIDIA A100-SXM4-40GB  utilization 0%    mem 39GB/40GB    temp 31\u00b0    User N/A"
    }
]